[
  {
    "id": "intro",
    "title": "르망24란 무엇인가요?",
    "content": "르망 24시(24 Hours of Le Mans)는 프랑스 사르트 서킷에서 개최되는 세계 최고 역사의 내구 레이스입니다. 1923년 첫 대회를 시작으로 매년 6월 개최되며, 세계 최고 성능의 레이싱카들이 24시간 동안 끊임없이 달리며 한계를 시험합니다. 단순히 속도만 겨루는 것이 아니라 차량의 내구성, 연비, 신뢰성이 모두 우승을 결정하는 핵심 요소입니다."
  },
  {
    "id": "purpose",
    "title": "경기의 목적과 우승 조건은?",
    "content": "르망 24시의 우승 조건은 심플합니다. '24시간 동안 가장 긴 거리를 주행한 차량이 승리한다'는 것입니다. 이를 위해 차량 한 대당 3명의 드라이버가 교대로 운전하며, 평균 시속 220km/h가 넘는 속도로 서킷을 주행합니다. 주행 거리 합산은 약 5,000km를 초과하기도 하며, 이는 서울과 부산을 약 6회 왕복하는 거리와 맞먹습니다."
  },
  {
    "id": "why24",
    "title": "왜 하필 24시간 동안 달리나요?",
    "content": "24시간 내구 레이스는 인간의 체력적 한계와 기계의 기계적 한계를 극한까지 밀어붙이기 위해 고안되었습니다. 낮과 밤, 그리고 다시 아침으로 이어지는 시간의 변화 속에서 기온 변화, 칠흑 같은 어둠 속에서의 야간 주행, 수시로 변하는 악천후를 극복해야 합니다. 완성차 제조사들은 이 혹독한 24시간의 시험대를 거쳐 양산차에 탑재할 미래 신기술(하이브리드 시스템, 고전압 배터리, 고효율 엔진 등)을 개발하고 검증해 왔습니다."
  }
]
